{
  "CP": {
    "types": [
      "meal_takeaway",
      "restaurant",
      "food",
      "point_of_interest",
      "establishment"
    ],
    "address": "53/c, Asad Ave, Dhaka 1207, Bangladesh",
    "name": "CP",
    "rating": 4.2,
    "periods": [
      {
        "close": {
          "time": "2200",
          "day": 0
        },
        "open": {
          "time": "1000",
          "day": 0
        }
      },
      {
        "close": {
          "time": "2200",
          "day": 1
        },
        "open": {
          "time": "1000",
          "day": 1
        }
      },
      {
        "close": {
          "time": "2200",
          "day": 2
        },
        "open": {
          "time": "1000",
          "day": 2
        }
      },
      {
        "close": {
          "time": "2200",
          "day": 3
        },
        "open": {
          "time": "1000",
          "day": 3
        }
      },
      {
        "close": {
          "time": "2200",
          "day": 4
        },
        "open": {
          "time": "1000",
          "day": 4
        }
      },
      {
        "close": {
          "time": "2200",
          "day": 5
        },
        "open": {
          "time": "1000",
          "day": 5
        }
      },
      {
        "close": {
          "time": "2200",
          "day": 6
        },
        "open": {
          "time": "1000",
          "day": 6
        }
      }
    ],
    "location": {
      "lng": 90.3626816,
      "lat": 23.7581533
    },
    "weekday_text": [
      "Monday: 10:00 AM \u2013 10:00 PM",
      "Tuesday: 10:00 AM \u2013 10:00 PM",
      "Wednesday: 10:00 AM \u2013 10:00 PM",
      "Thursday: 10:00 AM \u2013 10:00 PM",
      "Friday: 10:00 AM \u2013 10:00 PM",
      "Saturday: 10:00 AM \u2013 10:00 PM",
      "Sunday: 10:00 AM \u2013 10:00 PM"
    ],
    "url": "https://maps.google.com/?cid=77781364837793711"
  }
}